lpmpmessage.py
lpmptox.py
lpshipit.py
lxc.py
picker.py
setup.py
lpshipit-0.4.8.dist-info/LICENSE
lpshipit-0.4.8.dist-info/METADATA
lpshipit-0.4.8.dist-info/WHEEL
lpshipit-0.4.8.dist-info/entry_points.txt
lpshipit-0.4.8.dist-info/top_level.txt
lpshipit-0.4.8.dist-info/RECORD
