Metadata-Version: 2.1
Name: lpshipit
Version: 0.4.8
Summary: Helpful utility for merging launchpad MPs (only works for git repos)
Home-page: UNKNOWN
Author: philroche
Author-email: phil.roche@canonical.com
License: UNKNOWN
Platform: UNKNOWN
Requires-Dist: simplejson
Requires-Dist: click
Requires-Dist: urwid
Requires-Dist: GitPython
